[
    {
        "_unitTypeId": 1,
        "_name": "高坂穂乃果",
        "_nameAlpha": "HONOKA KOSAKA",
        "_age": "2",
        "_birthday": "8月3日",
        "_bloodType": "Ｏ型",
        "_height": "157",
        "_cv": "新田恵海",
        "_masterReleaseLabelId": 1
    },
    {
        "_unitTypeId": 2,
        "_name": "絢瀬絵里",
        "_nameAlpha": "ELI AYASE",
        "_age": "3",
        "_birthday": "10月21日",
        "_bloodType": "Ｂ型",
        "_height": "162",
        "_cv": "南條愛乃",
        "_masterReleaseLabelId": 1
    },
    {
        "_unitTypeId": 3,
        "_name": "南ことり",
        "_nameAlpha": "KOTORI MINAMI",
        "_age": "2",
        "_birthday": "9月12日",
        "_bloodType": "Ｏ型",
        "_height": "159",
        "_cv": "内田 彩",
        "_masterReleaseLabelId": 1
    },
    {
        "_unitTypeId": 4,
        "_name": "園田海未",
        "_nameAlpha": "UMI SONODA",
        "_age": "2",
        "_birthday": "3月15日",
        "_bloodType": "Ａ型",
        "_height": "159",
        "_cv": "三森すずこ",
        "_masterReleaseLabelId": 1
    },
    {
        "_unitTypeId": 5,
        "_name": "星空凛",
        "_nameAlpha": "RIN HOSHIZORA",
        "_age": "1",
        "_birthday": "11月1日",
        "_bloodType": "Ａ型",
        "_height": "155",
        "_cv": "飯田里穂",
        "_masterReleaseLabelId": 1
    },
    {
        "_unitTypeId": 6,
        "_name": "西木野真姫",
        "_nameAlpha": "MAKI NISHIKINO",
        "_age": "1",
        "_birthday": "4月19日",
        "_bloodType": "ＡＢ型",
        "_height": "161",
        "_cv": "Pile",
        "_masterReleaseLabelId": 1
    },
    {
        "_unitTypeId": 7,
        "_name": "東條希",
        "_nameAlpha": "NOZOMI TOJO",
        "_age": "3",
        "_birthday": "6月9日",
        "_bloodType": "Ｏ型",
        "_height": "159",
        "_cv": "楠田亜衣奈",
        "_masterReleaseLabelId": 1
    },
    {
        "_unitTypeId": 8,
        "_name": "小泉花陽",
        "_nameAlpha": "HANAYO KOIZUMI",
        "_age": "1",
        "_birthday": "1月17日",
        "_bloodType": "Ｂ型",
        "_height": "156",
        "_cv": "久保ユリカ",
        "_masterReleaseLabelId": 1
    },
    {
        "_unitTypeId": 9,
        "_name": "矢澤にこ",
        "_nameAlpha": "NICO YAZAWA",
        "_age": "3",
        "_birthday": "7月22日",
        "_bloodType": "Ａ型",
        "_height": "154",
        "_cv": "徳井青空",
        "_masterReleaseLabelId": 1
    },
    {
        "_unitTypeId": 10,
        "_name": "μ's",
        "_nameAlpha": "μ's",
        "_age": "？",
        "_birthday": "？月？日",
        "_bloodType": "？型",
        "_height": "？",
        "_cv": "？？？？",
        "_masterReleaseLabelId": 1
    },
    {
        "_unitTypeId": 11,
        "_name": "桜坂しずく",
        "_nameAlpha": "SHIZUKU OSAKA",
        "_age": "1",
        "_birthday": "4月3日",
        "_bloodType": "Ａ型",
        "_height": "157",
        "_cv": "？？？？",
        "_masterReleaseLabelId": 1
    },
    {
        "_unitTypeId": 12,
        "_name": "宮下ココ",
        "_nameAlpha": "COCO MIYASHITA",
        "_age": "1",
        "_birthday": "6月2日",
        "_bloodType": "Ａ型",
        "_height": "155",
        "_cv": "？？？？",
        "_masterReleaseLabelId": 1
    },
    {
        "_unitTypeId": 13,
        "_name": "逢沢遊宇",
        "_nameAlpha": "YUU AIZAWA",
        "_age": "1",
        "_birthday": "7月7日",
        "_bloodType": "Ｏ型",
        "_height": "157",
        "_cv": "？？？？",
        "_masterReleaseLabelId": 1
    },
    {
        "_unitTypeId": 14,
        "_name": "一之瀬マリカ",
        "_nameAlpha": "MARIKA ICHINOSE",
        "_age": "2",
        "_birthday": "4月20日",
        "_bloodType": "Ｂ型",
        "_height": "161",
        "_cv": "？？？？",
        "_masterReleaseLabelId": 1
    },
    {
        "_unitTypeId": 15,
        "_name": "結城紗菜",
        "_nameAlpha": "SANA YUKI",
        "_age": "2",
        "_birthday": "8月20日",
        "_bloodType": "Ｂ型",
        "_height": "160",
        "_cv": "？？？？",
        "_masterReleaseLabelId": 1
    },
    {
        "_unitTypeId": 16,
        "_name": "西村文絵",
        "_nameAlpha": "FUMIE NISHIMURA",
        "_age": "2",
        "_birthday": "9月20日",
        "_bloodType": "Ｂ型",
        "_height": "156",
        "_cv": "？？？？",
        "_masterReleaseLabelId": 1
    },
    {
        "_unitTypeId": 17,
        "_name": "永山みなみ",
        "_nameAlpha": "MINAMI NAGAYAMA",
        "_age": "3",
        "_birthday": "8月30日",
        "_bloodType": "Ｏ型",
        "_height": "163",
        "_cv": "？？？？",
        "_masterReleaseLabelId": 1
    },
    {
        "_unitTypeId": 18,
        "_name": "クリスティーナ",
        "_nameAlpha": "CHRISTINA",
        "_age": "3",
        "_birthday": "1月21日",
        "_bloodType": "Ａ型",
        "_height": "161",
        "_cv": "？？？？",
        "_masterReleaseLabelId": 1
    },
    {
        "_unitTypeId": 19,
        "_name": "菊池朱美",
        "_nameAlpha": "AKEMI KIKUCHI",
        "_age": "3",
        "_birthday": "10月30日",
        "_bloodType": "Ｂ型",
        "_height": "160",
        "_cv": "？？？？",
        "_masterReleaseLabelId": 1
    },
    {
        "_unitTypeId": 20,
        "_name": "須田いるか",
        "_nameAlpha": "IRUKA SUDA",
        "_age": "1",
        "_birthday": "2月18日",
        "_bloodType": "Ｏ型",
        "_height": "159",
        "_cv": "？？？？",
        "_masterReleaseLabelId": 1
    },
    {
        "_unitTypeId": 21,
        "_name": "杉崎亜矢",
        "_nameAlpha": "AYA SUGISAKI",
        "_age": "1",
        "_birthday": "9月30日",
        "_bloodType": "Ｏ型",
        "_height": "153",
        "_cv": "？？？？",
        "_masterReleaseLabelId": 1
    },
    {
        "_unitTypeId": 22,
        "_name": "御堂優理",
        "_nameAlpha": "YURI MIDO",
        "_age": "1",
        "_birthday": "12月24日",
        "_bloodType": "Ａ型",
        "_height": "164",
        "_cv": "？？？？",
        "_masterReleaseLabelId": 1
    },
    {
        "_unitTypeId": 23,
        "_name": "佐伯麗音",
        "_nameAlpha": "REINE SAEKI",
        "_age": "2",
        "_birthday": "6月16日",
        "_bloodType": "Ａ型",
        "_height": "155",
        "_cv": "？？？？",
        "_masterReleaseLabelId": 1
    },
    {
        "_unitTypeId": 24,
        "_name": "鳥居歩美",
        "_nameAlpha": "AYUMI TORII",
        "_age": "2",
        "_birthday": "3月8日",
        "_bloodType": "Ａ型",
        "_height": "154",
        "_cv": "？？？？",
        "_masterReleaseLabelId": 1
    },
    {
        "_unitTypeId": 25,
        "_name": "神谷理華",
        "_nameAlpha": "RIKA KAMIYA",
        "_age": "2",
        "_birthday": "1月7日",
        "_bloodType": "Ａ型",
        "_height": "159",
        "_cv": "？？？？",
        "_masterReleaseLabelId": 1
    },
    {
        "_unitTypeId": 26,
        "_name": "森嶋ななか",
        "_nameAlpha": "NANAKA MORISHIMA",
        "_age": "3",
        "_birthday": "3月7日",
        "_bloodType": "Ｂ型",
        "_height": "163",
        "_cv": "？？？？",
        "_masterReleaseLabelId": 1
    },
    {
        "_unitTypeId": 27,
        "_name": "九条聖来",
        "_nameAlpha": "SEIRA KUJO",
        "_age": "3",
        "_birthday": "11月15日",
        "_bloodType": "Ｏ型",
        "_height": "158",
        "_cv": "？？？？",
        "_masterReleaseLabelId": 1
    },
    {
        "_unitTypeId": 28,
        "_name": "近江彼方",
        "_nameAlpha": "KANATA KONOE",
        "_age": "3",
        "_birthday": "12月16日",
        "_bloodType": "Ｏ型",
        "_height": "158",
        "_cv": "？？？？",
        "_masterReleaseLabelId": 1
    },
    {
        "_unitTypeId": 29,
        "_name": "近江遥",
        "_nameAlpha": "HARUKA KONOE",
        "_age": "1",
        "_birthday": "11月11日",
        "_bloodType": "Ａ型",
        "_height": "154",
        "_cv": "？？？？",
        "_masterReleaseLabelId": 1
    },
    {
        "_unitTypeId": 30,
        "_name": "下園咲",
        "_nameAlpha": "SAKI SHIMOZONO",
        "_age": "1",
        "_birthday": "5月5日",
        "_bloodType": "Ａ型",
        "_height": "158",
        "_cv": "？？？？",
        "_masterReleaseLabelId": 1
    },
    {
        "_unitTypeId": 31,
        "_name": "田中さち子",
        "_nameAlpha": "SACHIKO TANAKA",
        "_age": "1",
        "_birthday": "9月3日",
        "_bloodType": "ＡＢ型",
        "_height": "156",
        "_cv": "？？？？",
        "_masterReleaseLabelId": 1
    },
    {
        "_unitTypeId": 32,
        "_name": "支倉かさね",
        "_nameAlpha": "KASANE HASEKURA",
        "_age": "2",
        "_birthday": "12月12日",
        "_bloodType": "Ｏ型",
        "_height": "161",
        "_cv": "？？？？",
        "_masterReleaseLabelId": 1
    },
    {
        "_unitTypeId": 33,
        "_name": "多々良るう",
        "_nameAlpha": "RU TATARA",
        "_age": "2",
        "_birthday": "3月25日",
        "_bloodType": "Ａ型",
        "_height": "152",
        "_cv": "？？？？",
        "_masterReleaseLabelId": 1
    },
    {
        "_unitTypeId": 34,
        "_name": "篠宮あきる",
        "_nameAlpha": "AKIRU SHINOMIYA",
        "_age": "2",
        "_birthday": "7月20日",
        "_bloodType": "Ｏ型",
        "_height": "160",
        "_cv": "？？？？",
        "_masterReleaseLabelId": 1
    },
    {
        "_unitTypeId": 35,
        "_name": "吉川瑞希",
        "_nameAlpha": "MIZUKI KIKKAWA",
        "_age": "3",
        "_birthday": "10月20日",
        "_bloodType": "Ａ型",
        "_height": "167",
        "_cv": "？？？？",
        "_masterReleaseLabelId": 1
    },
    {
        "_unitTypeId": 36,
        "_name": "白木凪",
        "_nameAlpha": "NAGI SHIRAKI",
        "_age": "3",
        "_birthday": "2月9日",
        "_bloodType": "Ｂ型",
        "_height": "150",
        "_cv": "？？？？",
        "_masterReleaseLabelId": 1
    },
    {
        "_unitTypeId": 37,
        "_name": "藤城悠弓",
        "_nameAlpha": "YUMI FUJISHIRO",
        "_age": "3",
        "_birthday": "5月15日",
        "_bloodType": "ＡＢ型",
        "_height": "165",
        "_cv": "？？？？",
        "_masterReleaseLabelId": 1
    },
    {
        "_unitTypeId": 38,
        "_name": "深山聡子",
        "_nameAlpha": "SATOKO MIYAMA",
        "_age": "？",
        "_birthday": "6月8日",
        "_bloodType": "Ｏ型",
        "_height": "164",
        "_cv": "？？？？",
        "_masterReleaseLabelId": 1
    },
    {
        "_unitTypeId": 39,
        "_name": "山内奈々子",
        "_nameAlpha": "NANAKO YAMAUCHI",
        "_age": "？",
        "_birthday": "12月8日",
        "_bloodType": "Ａ型",
        "_height": "153",
        "_cv": "？？？？",
        "_masterReleaseLabelId": 1
    },
    {
        "_unitTypeId": 40,
        "_name": "笹原京子",
        "_nameAlpha": "KYOKO SASAHARA",
        "_age": "？",
        "_birthday": "9月8日",
        "_bloodType": "Ｂ型",
        "_height": "168",
        "_cv": "？？？？",
        "_masterReleaseLabelId": 1
    },
    {
        "_unitTypeId": 41,
        "_name": "黒崎隼",
        "_nameAlpha": "SHUN KUROSAKI",
        "_age": "2",
        "_birthday": "6月15日",
        "_bloodType": "Ｏ型",
        "_height": "163",
        "_cv": "？？？？",
        "_masterReleaseLabelId": 1
    },
    {
        "_unitTypeId": 42,
        "_name": "設楽ふみ",
        "_nameAlpha": "FUMI SHITARA",
        "_age": "1",
        "_birthday": "3月20日",
        "_bloodType": "ＡＢ型",
        "_height": "151",
        "_cv": "？？？？",
        "_masterReleaseLabelId": 1
    },
    {
        "_unitTypeId": 43,
        "_name": "門田剣",
        "_nameAlpha": "TSURUGI KADOTA",
        "_age": "3",
        "_birthday": "7月10日",
        "_bloodType": "Ａ型",
        "_height": "168",
        "_cv": "？？？？",
        "_masterReleaseLabelId": 1
    },
    {
        "_unitTypeId": 44,
        "_name": "アルパカ[白]",
        "_nameAlpha": "alpaca",
        "_age": "？",
        "_birthday": "？月？日",
        "_bloodType": "？型",
        "_height": "？",
        "_cv": "？？？？",
        "_masterReleaseLabelId": 1
    },
    {
        "_unitTypeId": 45,
        "_name": "桐原優香",
        "_nameAlpha": "YUUKA KIRIHARA",
        "_age": "2",
        "_birthday": "4月2日",
        "_bloodType": "Ａ型",
        "_height": "158",
        "_cv": "？？？？",
        "_masterReleaseLabelId": 1
    },
    {
        "_unitTypeId": 46,
        "_name": "斉木風",
        "_nameAlpha": "FUU SAIKI",
        "_age": "1",
        "_birthday": "8月12日",
        "_bloodType": "Ｏ型",
        "_height": "162",
        "_cv": "？？？？",
        "_masterReleaseLabelId": 1
    },
    {
        "_unitTypeId": 47,
        "_name": "福原命",
        "_nameAlpha": "MIKOTO FUKUHARA",
        "_age": "1",
        "_birthday": "11月5日",
        "_bloodType": "Ａ型",
        "_height": "147",
        "_cv": "？？？？",
        "_masterReleaseLabelId": 1
    },
    {
        "_unitTypeId": 48,
        "_name": "坂巻千鶴子",
        "_nameAlpha": "CHIDUKO SAKAMAKI",
        "_age": "2",
        "_birthday": "7月14日",
        "_bloodType": "Ｏ型",
        "_height": "162",
        "_cv": "？？？？",
        "_masterReleaseLabelId": 1
    },
    {
        "_unitTypeId": 49,
        "_name": "志賀仁美",
        "_nameAlpha": "HITOMI SHIGA",
        "_age": "3",
        "_birthday": "6月6日",
        "_bloodType": "Ｂ型",
        "_height": "167",
        "_cv": "？？？？",
        "_masterReleaseLabelId": 1
    },
    {
        "_unitTypeId": 50,
        "_name": "鬼崎アキラ",
        "_nameAlpha": "AKIRA KIZAKI",
        "_age": "2",
        "_birthday": "8月10日",
        "_bloodType": "Ａ型",
        "_height": "164",
        "_cv": "？？？？",
        "_masterReleaseLabelId": 1
    },
    {
        "_unitTypeId": 51,
        "_name": "紫藤美咲",
        "_nameAlpha": "MISAKI SHIDO",
        "_age": "3",
        "_birthday": "4月7日",
        "_bloodType": "ＡＢ型",
        "_height": "167",
        "_cv": "？？？？",
        "_masterReleaseLabelId": 1
    },
    {
        "_unitTypeId": 52,
        "_name": "月島結架",
        "_nameAlpha": "YUKA TSUKISHIMA",
        "_age": "2",
        "_birthday": "7月21日",
        "_bloodType": "Ｂ型",
        "_height": "158",
        "_cv": "？？？？",
        "_masterReleaseLabelId": 1
    },
    {
        "_unitTypeId": 53,
        "_name": "兵藤さゆり",
        "_nameAlpha": "SAYURI HYODO",
        "_age": "3",
        "_birthday": "4月22日",
        "_bloodType": "Ｏ型",
        "_height": "163",
        "_cv": "？？？？",
        "_masterReleaseLabelId": 1
    },
    {
        "_unitTypeId": 54,
        "_name": "蘭花",
        "_nameAlpha": "RANPHA",
        "_age": "1",
        "_birthday": "2月8日",
        "_bloodType": "Ａ型",
        "_height": "154",
        "_cv": "？？？？",
        "_masterReleaseLabelId": 1
    },
    {
        "_unitTypeId": 55,
        "_name": "ラクシャータ",
        "_nameAlpha": "RAKSHATA",
        "_age": "2",
        "_birthday": "6月18日",
        "_bloodType": "Ｏ型",
        "_height": "157",
        "_cv": "？？？？",
        "_masterReleaseLabelId": 1
    },
    {
        "_unitTypeId": 56,
        "_name": "レベッカ",
        "_nameAlpha": "REBECCA",
        "_age": "2",
        "_birthday": "11月14日",
        "_bloodType": "Ａ型",
        "_height": "167",
        "_cv": "？？？？",
        "_masterReleaseLabelId": 1
    },
    {
        "_unitTypeId": 57,
        "_name": "綾小路姫乃",
        "_nameAlpha": "HIMENO AYANOKOJI",
        "_age": "2",
        "_birthday": "4月17日",
        "_bloodType": "Ａ型",
        "_height": "158",
        "_cv": "？？？？",
        "_masterReleaseLabelId": 1
    },
    {
        "_unitTypeId": 58,
        "_name": "黒羽咲良",
        "_nameAlpha": "SAKURA KUROBANE",
        "_age": "1",
        "_birthday": "4月4日",
        "_bloodType": "ＡＢ型",
        "_height": "162",
        "_cv": "？？？？",
        "_masterReleaseLabelId": 1
    },
    {
        "_unitTypeId": 59,
        "_name": "黒羽咲夜",
        "_nameAlpha": "SAKUYA KUROBANE",
        "_age": "3",
        "_birthday": "9月9日",
        "_bloodType": "ＡＢ型",
        "_height": "160",
        "_cv": "？？？？",
        "_masterReleaseLabelId": 1
    },
    {
        "_unitTypeId": 60,
        "_name": "白瀬小雪",
        "_nameAlpha": "KOYUKI SHIRASE",
        "_age": "1",
        "_birthday": "2月23日",
        "_bloodType": "Ｂ型",
        "_height": "147",
        "_cv": "？？？？",
        "_masterReleaseLabelId": 1
    },
    {
        "_unitTypeId": 61,
        "_name": "相川涼",
        "_nameAlpha": "RYO AIKAWA",
        "_age": "3",
        "_birthday": "5月6日",
        "_bloodType": "ＡＢ型",
        "_height": "168",
        "_cv": "？？？？",
        "_masterReleaseLabelId": 1
    },
    {
        "_unitTypeId": 62,
        "_name": "イザベラ",
        "_nameAlpha": "ISABELLA",
        "_age": "3",
        "_birthday": "11月16日",
        "_bloodType": "Ｂ型",
        "_height": "162",
        "_cv": "？？？？",
        "_masterReleaseLabelId": 1
    },
    {
        "_unitTypeId": 63,
        "_name": "エマ・ヴェルデ",
        "_nameAlpha": "EMMA VERDE",
        "_age": "3",
        "_birthday": "2月5日",
        "_bloodType": "Ｏ型",
        "_height": "166",
        "_cv": "？？？？",
        "_masterReleaseLabelId": 1
    },
    {
        "_unitTypeId": 64,
        "_name": "高天原睦月",
        "_nameAlpha": "MUTSUKI TAKAMAGAHARA",
        "_age": "1",
        "_birthday": "1月25日",
        "_bloodType": "ＡＢ型",
        "_height": "148",
        "_cv": "？？？？",
        "_masterReleaseLabelId": 1
    },
    {
        "_unitTypeId": 65,
        "_name": "ジェニファー",
        "_nameAlpha": "JENNIFER",
        "_age": "2",
        "_birthday": "5月12日",
        "_bloodType": "Ａ型",
        "_height": "165",
        "_cv": "？？？？",
        "_masterReleaseLabelId": 1
    },
    {
        "_unitTypeId": 66,
        "_name": "マリア",
        "_nameAlpha": "MARIA",
        "_age": "1",
        "_birthday": "8月6日",
        "_bloodType": "Ａ型",
        "_height": "163",
        "_cv": "？？？？",
        "_masterReleaseLabelId": 1
    },
    {
        "_unitTypeId": 67,
        "_name": "レオ",
        "_nameAlpha": "LEO",
        "_age": "2",
        "_birthday": "8月16日",
        "_bloodType": "ＡＢ型",
        "_height": "151",
        "_cv": "？？？？",
        "_masterReleaseLabelId": 1
    },
    {
        "_unitTypeId": 68,
        "_name": "早乙女紫",
        "_nameAlpha": "YUKARI SAOTOME",
        "_age": "1",
        "_birthday": "3月3日",
        "_bloodType": "Ｏ型",
        "_height": "158",
        "_cv": "？？？？",
        "_masterReleaseLabelId": 1
    },
    {
        "_unitTypeId": 69,
        "_name": "矢澤ここあ",
        "_nameAlpha": "COCOA YAZAWA",
        "_age": "？",
        "_birthday": "？月？日",
        "_bloodType": "？型",
        "_height": "？",
        "_cv": "？？？？",
        "_masterReleaseLabelId": 1
    },
    {
        "_unitTypeId": 70,
        "_name": "矢澤虎太郎",
        "_nameAlpha": "COTARO YAZAWA",
        "_age": "？",
        "_birthday": "？月？日",
        "_bloodType": "？型",
        "_height": "？",
        "_cv": "？？？？",
        "_masterReleaseLabelId": 1
    },
    {
        "_unitTypeId": 71,
        "_name": "矢澤こころ",
        "_nameAlpha": "COCORO YAZAWA",
        "_age": "？",
        "_birthday": "？月？日",
        "_bloodType": "？型",
        "_height": "？",
        "_cv": "？？？？",
        "_masterReleaseLabelId": 1
    },
    {
        "_unitTypeId": 72,
        "_name": "ミカ",
        "_nameAlpha": "MIKA",
        "_age": "2",
        "_birthday": "？月？日",
        "_bloodType": "？型",
        "_height": "？",
        "_cv": "？？？？",
        "_masterReleaseLabelId": 1
    },
    {
        "_unitTypeId": 73,
        "_name": "フミコ",
        "_nameAlpha": "FUMIKO",
        "_age": "2",
        "_birthday": "？月？日",
        "_bloodType": "？型",
        "_height": "？",
        "_cv": "？？？？",
        "_masterReleaseLabelId": 1
    },
    {
        "_unitTypeId": 74,
        "_name": "ヒデコ",
        "_nameAlpha": "HIDEKO",
        "_age": "2",
        "_birthday": "？月？日",
        "_bloodType": "？型",
        "_height": "？",
        "_cv": "？？？？",
        "_masterReleaseLabelId": 1
    },
    {
        "_unitTypeId": 75,
        "_name": "山田博子",
        "_nameAlpha": "HIROKO YAMADA",
        "_age": "？",
        "_birthday": "？月？日",
        "_bloodType": "？型",
        "_height": "？",
        "_cv": "？？？？",
        "_masterReleaseLabelId": 1
    },
    {
        "_unitTypeId": 76,
        "_name": "にこの母",
        "_nameAlpha": "NICO'S MOTHER",
        "_age": "？",
        "_birthday": "？月？日",
        "_bloodType": "？型",
        "_height": "？",
        "_cv": "？？？？",
        "_masterReleaseLabelId": 1
    },
    {
        "_unitTypeId": 77,
        "_name": "ことりの母",
        "_nameAlpha": "KOTORI'S MOTHER",
        "_age": "？",
        "_birthday": "？月？日",
        "_bloodType": "？型",
        "_height": "？",
        "_cv": "？？？？",
        "_masterReleaseLabelId": 1
    },
    {
        "_unitTypeId": 78,
        "_name": "真姫の母",
        "_nameAlpha": "MAKI'S MOTHER",
        "_age": "？",
        "_birthday": "？月？日",
        "_bloodType": "？型",
        "_height": "？",
        "_cv": "？？？？",
        "_masterReleaseLabelId": 1
    },
    {
        "_unitTypeId": 79,
        "_name": "穂乃果の母",
        "_nameAlpha": "HONOKA'S MOTHER",
        "_age": "？",
        "_birthday": "？月？日",
        "_bloodType": "？型",
        "_height": "？",
        "_cv": "？？？？",
        "_masterReleaseLabelId": 1
    },
    {
        "_unitTypeId": 80,
        "_name": "綺羅ツバサ",
        "_nameAlpha": "TSUBASA KIRA",
        "_age": "3",
        "_birthday": "？月？日",
        "_bloodType": "？型",
        "_height": "？",
        "_cv": "桜川めぐ",
        "_masterReleaseLabelId": 1
    },
    {
        "_unitTypeId": 81,
        "_name": "優木あんじゅ",
        "_nameAlpha": "ANJU YUKI",
        "_age": "3",
        "_birthday": "？月？日",
        "_bloodType": "？型",
        "_height": "？",
        "_cv": "大橋歩夕",
        "_masterReleaseLabelId": 1
    },
    {
        "_unitTypeId": 82,
        "_name": "統堂英玲奈",
        "_nameAlpha": "ERENA TODO",
        "_age": "3",
        "_birthday": "？月？日",
        "_bloodType": "？型",
        "_height": "？",
        "_cv": "松永真穂",
        "_masterReleaseLabelId": 1
    },
    {
        "_unitTypeId": 83,
        "_name": "アルパカ[茶]",
        "_nameAlpha": "alpaca",
        "_age": "？",
        "_birthday": "？月？日",
        "_bloodType": "？型",
        "_height": "？",
        "_cv": "？？？？",
        "_masterReleaseLabelId": 1
    },
    {
        "_unitTypeId": 84,
        "_name": "μ's",
        "_nameAlpha": "μ's",
        "_age": "？",
        "_birthday": "？月？日",
        "_bloodType": "？型",
        "_height": "？",
        "_cv": "？？？？",
        "_masterReleaseLabelId": 1
    },
    {
        "_unitTypeId": 85,
        "_name": "アルパカの子ども",
        "_nameAlpha": "alpaca's child",
        "_age": "？",
        "_birthday": "？月？日",
        "_bloodType": "？型",
        "_height": "？",
        "_cv": "？？？？",
        "_masterReleaseLabelId": 1
    },
    {
        "_unitTypeId": 86,
        "_name": "絢瀬亜里沙",
        "_nameAlpha": "ALISA AYASE",
        "_age": "？",
        "_birthday": "？月？日",
        "_bloodType": "？型",
        "_height": "？",
        "_cv": "？？？？",
        "_masterReleaseLabelId": 1
    },
    {
        "_unitTypeId": 91,
        "_name": "高坂穂乃果",
        "_nameAlpha": "HONOKA KOSAKA",
        "_age": "？",
        "_birthday": "8月3日",
        "_bloodType": "Ｏ型",
        "_height": "？",
        "_cv": "新田恵海",
        "_masterReleaseLabelId": 1
    },
    {
        "_unitTypeId": 92,
        "_name": "絢瀬絵里",
        "_nameAlpha": "ELI AYASE",
        "_age": "？",
        "_birthday": "10月21日",
        "_bloodType": "Ｂ型",
        "_height": "？",
        "_cv": "南條愛乃",
        "_masterReleaseLabelId": 1
    },
    {
        "_unitTypeId": 93,
        "_name": "南ことり",
        "_nameAlpha": "KOTORI MINAMI",
        "_age": "？",
        "_birthday": "9月12日",
        "_bloodType": "Ｏ型",
        "_height": "？",
        "_cv": "内田 彩",
        "_masterReleaseLabelId": 1
    },
    {
        "_unitTypeId": 94,
        "_name": "園田海未",
        "_nameAlpha": "UMI SONODA",
        "_age": "？",
        "_birthday": "3月15日",
        "_bloodType": "Ａ型",
        "_height": "？",
        "_cv": "三森すずこ",
        "_masterReleaseLabelId": 1
    },
    {
        "_unitTypeId": 95,
        "_name": "星空凛",
        "_nameAlpha": "RIN HOSHIZORA",
        "_age": "？",
        "_birthday": "11月1日",
        "_bloodType": "Ａ型",
        "_height": "？",
        "_cv": "飯田里穂",
        "_masterReleaseLabelId": 1
    },
    {
        "_unitTypeId": 96,
        "_name": "西木野真姫",
        "_nameAlpha": "MAKI NISHIKINO",
        "_age": "？",
        "_birthday": "4月19日",
        "_bloodType": "ＡＢ型",
        "_height": "？",
        "_cv": "Pile",
        "_masterReleaseLabelId": 1
    },
    {
        "_unitTypeId": 97,
        "_name": "東條希",
        "_nameAlpha": "NOZOMI TOJO",
        "_age": "？",
        "_birthday": "6月9日",
        "_bloodType": "Ｏ型",
        "_height": "？",
        "_cv": "楠田亜衣奈",
        "_masterReleaseLabelId": 1
    },
    {
        "_unitTypeId": 98,
        "_name": "小泉花陽",
        "_nameAlpha": "HANAYO KOIZUMI",
        "_age": "？",
        "_birthday": "1月17日",
        "_bloodType": "Ｂ型",
        "_height": "？",
        "_cv": "久保ユリカ",
        "_masterReleaseLabelId": 1
    },
    {
        "_unitTypeId": 99,
        "_name": "矢澤にこ",
        "_nameAlpha": "NICO YAZAWA",
        "_age": "？",
        "_birthday": "7月22日",
        "_bloodType": "Ａ型",
        "_height": "？",
        "_cv": "徳井青空",
        "_masterReleaseLabelId": 1
    },
    {
        "_unitTypeId": 101,
        "_name": "高海千歌",
        "_nameAlpha": "CHIKA TAKAMI",
        "_age": "2",
        "_birthday": "8月1日",
        "_bloodType": "Ｂ型",
        "_height": "157",
        "_cv": "伊波杏樹",
        "_masterReleaseLabelId": 1
    },
    {
        "_unitTypeId": 102,
        "_name": "桜内梨子",
        "_nameAlpha": "RIKO SAKURAUCHI",
        "_age": "2",
        "_birthday": "9月19日",
        "_bloodType": "Ａ型",
        "_height": "160",
        "_cv": "逢田梨香子",
        "_masterReleaseLabelId": 1
    },
    {
        "_unitTypeId": 103,
        "_name": "松浦果南",
        "_nameAlpha": "KANAN MATSUURA",
        "_age": "3",
        "_birthday": "2月10日",
        "_bloodType": "Ｏ型",
        "_height": "162",
        "_cv": "諏訪ななか",
        "_masterReleaseLabelId": 1
    },
    {
        "_unitTypeId": 104,
        "_name": "黒澤ダイヤ",
        "_nameAlpha": "DIA KUROSAWA",
        "_age": "3",
        "_birthday": "1月1日",
        "_bloodType": "Ａ型",
        "_height": "162",
        "_cv": "小宮有紗",
        "_masterReleaseLabelId": 1
    },
    {
        "_unitTypeId": 105,
        "_name": "渡辺曜",
        "_nameAlpha": "YOU WATANABE",
        "_age": "2",
        "_birthday": "4月17日",
        "_bloodType": "ＡＢ型",
        "_height": "157",
        "_cv": "斉藤朱夏",
        "_masterReleaseLabelId": 1
    },
    {
        "_unitTypeId": 106,
        "_name": "津島善子",
        "_nameAlpha": "YOSHIKO TSUSHIMA",
        "_age": "1",
        "_birthday": "7月13日",
        "_bloodType": "Ｏ型",
        "_height": "156",
        "_cv": "小林愛香",
        "_masterReleaseLabelId": 1
    },
    {
        "_unitTypeId": 107,
        "_name": "国木田花丸",
        "_nameAlpha": "HANAMARU KUNIKIDA",
        "_age": "1",
        "_birthday": "3月4日",
        "_bloodType": "Ｏ型",
        "_height": "152",
        "_cv": "高槻かなこ",
        "_masterReleaseLabelId": 1
    },
    {
        "_unitTypeId": 108,
        "_name": "小原鞠莉",
        "_nameAlpha": "MARI OHARA",
        "_age": "3",
        "_birthday": "6月13日",
        "_bloodType": "ＡＢ型",
        "_height": "163",
        "_cv": "鈴木愛奈",
        "_masterReleaseLabelId": 1
    },
    {
        "_unitTypeId": 109,
        "_name": "黒澤ルビィ",
        "_nameAlpha": "RUBY KUROSAWA",
        "_age": "1",
        "_birthday": "9月21日",
        "_bloodType": "Ａ型",
        "_height": "154",
        "_cv": "降幡 愛",
        "_masterReleaseLabelId": 1
    },
    {
        "_unitTypeId": 110,
        "_name": "Aqours",
        "_nameAlpha": "",
        "_age": "？",
        "_birthday": "？月？日",
        "_bloodType": "？型",
        "_height": "？",
        "_cv": "？？？？",
        "_masterReleaseLabelId": 1
    },
    {
        "_unitTypeId": 111,
        "_name": "しいたけ",
        "_nameAlpha": "SHIITAKE",
        "_age": "？",
        "_birthday": "？月？日",
        "_bloodType": "？型",
        "_height": "？",
        "_cv": "？？？？",
        "_masterReleaseLabelId": 1
    },
    {
        "_unitTypeId": 112,
        "_name": "鹿角理亞",
        "_nameAlpha": "LEAH KAZUNO",
        "_age": "1",
        "_birthday": "12月12日",
        "_bloodType": "ＡＢ型",
        "_height": "153",
        "_cv": "佐藤日向",
        "_masterReleaseLabelId": 1
    },
    {
        "_unitTypeId": 113,
        "_name": "鹿角聖良",
        "_nameAlpha": "SARAH KAZUNO",
        "_age": "3",
        "_birthday": "5月4日",
        "_bloodType": "Ａ型",
        "_height": "162",
        "_cv": "田野アサミ",
        "_masterReleaseLabelId": 1
    },
    {
        "_unitTypeId": 114,
        "_name": "うちっちー",
        "_nameAlpha": "UCHICCHI",
        "_age": "？",
        "_birthday": "？月？日",
        "_bloodType": "？型",
        "_height": "？",
        "_cv": "？？？？",
        "_masterReleaseLabelId": 1
    },
    {
        "_unitTypeId": 115,
        "_name": "千歌の母",
        "_nameAlpha": "CHIKA'S MOTHER",
        "_age": "？",
        "_birthday": "？月？日",
        "_bloodType": "？型",
        "_height": "？",
        "_cv": "？？？？",
        "_masterReleaseLabelId": 1
    },
    {
        "_unitTypeId": 116,
        "_name": "佐藤洋子",
        "_nameAlpha": "YOKO SATO",
        "_age": "？",
        "_birthday": "？月？日",
        "_bloodType": "？型",
        "_height": "？",
        "_cv": "？？？？",
        "_masterReleaseLabelId": 1
    },
    {
        "_unitTypeId": 117,
        "_name": "わたあめ",
        "_nameAlpha": "WATAAME",
        "_age": "？",
        "_birthday": "？月？日",
        "_bloodType": "？型",
        "_height": "？",
        "_cv": "？？？？",
        "_masterReleaseLabelId": 1
    },
    {
        "_unitTypeId": 118,
        "_name": "よしみ",
        "_nameAlpha": "YOSHIMI",
        "_age": "2",
        "_birthday": "？月？日",
        "_bloodType": "？型",
        "_height": "？",
        "_cv": "？？？？",
        "_masterReleaseLabelId": 1
    },
    {
        "_unitTypeId": 119,
        "_name": "いつき",
        "_nameAlpha": "ITSUKI",
        "_age": "2",
        "_birthday": "？月？日",
        "_bloodType": "？型",
        "_height": "？",
        "_cv": "？？？？",
        "_masterReleaseLabelId": 1
    },
    {
        "_unitTypeId": 120,
        "_name": "むつ",
        "_nameAlpha": "MUTSU",
        "_age": "2",
        "_birthday": "？月？日",
        "_bloodType": "？型",
        "_height": "？",
        "_cv": "？？？？",
        "_masterReleaseLabelId": 1
    },
    {
        "_unitTypeId": 121,
        "_name": "高海美渡",
        "_nameAlpha": "MITO TAKAMI",
        "_age": "？",
        "_birthday": "？月？日",
        "_bloodType": "？型",
        "_height": "？",
        "_cv": "？？？？",
        "_masterReleaseLabelId": 1
    },
    {
        "_unitTypeId": 122,
        "_name": "高海志満",
        "_nameAlpha": "SHIMA TAKAMI",
        "_age": "？",
        "_birthday": "？月？日",
        "_bloodType": "？型",
        "_height": "？",
        "_cv": "？？？？",
        "_masterReleaseLabelId": 1
    },
    {
        "_unitTypeId": 123,
        "_name": "梨子の母",
        "_nameAlpha": "RIKO'S MOTHER",
        "_age": "？",
        "_birthday": "？月？日",
        "_bloodType": "？型",
        "_height": "？",
        "_cv": "？？？？",
        "_masterReleaseLabelId": 1
    },
    {
        "_unitTypeId": 124,
        "_name": "Aqours",
        "_nameAlpha": "Aqours",
        "_age": "？",
        "_birthday": "？月？日",
        "_bloodType": "？型",
        "_height": "？",
        "_cv": "？？？？",
        "_masterReleaseLabelId": 1
    },
    {
        "_unitTypeId": 125,
        "_name": "しいたけの子ども",
        "_nameAlpha": "SHIITAKE'S CHILDREN",
        "_age": "？",
        "_birthday": "？月？日",
        "_bloodType": "？型",
        "_height": "？",
        "_cv": "？？？？",
        "_masterReleaseLabelId": 1
    },
    {
        "_unitTypeId": 126,
        "_name": "あんこ",
        "_nameAlpha": "Anko",
        "_age": "？",
        "_birthday": "？月？日",
        "_bloodType": "？型",
        "_height": "？",
        "_cv": "？？？？",
        "_masterReleaseLabelId": 1
    },
    {
        "_unitTypeId": 127,
        "_name": "ブロッサム",
        "_nameAlpha": "BLOSSOM",
        "_age": "？",
        "_birthday": "？月？日",
        "_bloodType": "？型",
        "_height": "？",
        "_cv": "？？？？",
        "_masterReleaseLabelId": 1
    },
    {
        "_unitTypeId": 128,
        "_name": "バブルス",
        "_nameAlpha": "BUBBLES",
        "_age": "？",
        "_birthday": "？月？日",
        "_bloodType": "？型",
        "_height": "？",
        "_cv": "？？？？",
        "_masterReleaseLabelId": 1
    },
    {
        "_unitTypeId": 129,
        "_name": "バターカップ",
        "_nameAlpha": "BUTTERCUP",
        "_age": "？",
        "_birthday": "？月？日",
        "_bloodType": "？型",
        "_height": "？",
        "_cv": "？？？？",
        "_masterReleaseLabelId": 1
    },
    {
        "_unitTypeId": 130,
        "_name": "渡辺月",
        "_nameAlpha": "TSUKI WATANABE",
        "_age": "？",
        "_birthday": "？月？日",
        "_bloodType": "？型",
        "_height": "？",
        "_cv": "？？？？",
        "_masterReleaseLabelId": 1
    },
    {
        "_unitTypeId": 131,
        "_name": "しんのすけ",
        "_nameAlpha": "SHINNOSUKE",
        "_age": "？",
        "_birthday": "？月？日",
        "_bloodType": "？型",
        "_height": "？",
        "_cv": "？？？？",
        "_masterReleaseLabelId": 1
    },
    {
        "_unitTypeId": 134,
        "_name": "ひまわり",
        "_nameAlpha": "HIMAWARI",
        "_age": "？",
        "_birthday": "？月？日",
        "_bloodType": "？型",
        "_height": "？",
        "_cv": "？？？？",
        "_masterReleaseLabelId": 1
    },
    {
        "_unitTypeId": 135,
        "_name": "シロ",
        "_nameAlpha": "SHIRO",
        "_age": "？",
        "_birthday": "？月？日",
        "_bloodType": "？型",
        "_height": "？",
        "_cv": "？？？？",
        "_masterReleaseLabelId": 1
    },
    {
        "_unitTypeId": 136,
        "_name": "しんちゃん",
        "_nameAlpha": "SHINCHAN",
        "_age": "？",
        "_birthday": "？月？日",
        "_bloodType": "？型",
        "_height": "？",
        "_cv": "？？？？",
        "_masterReleaseLabelId": 1
    },
    {
        "_unitTypeId": 137,
        "_name": "ボーちゃん",
        "_nameAlpha": "BO-CHAN",
        "_age": "？",
        "_birthday": "？月？日",
        "_bloodType": "？型",
        "_height": "？",
        "_cv": "？？？？",
        "_masterReleaseLabelId": 1
    },
    {
        "_unitTypeId": 138,
        "_name": "風間くん",
        "_nameAlpha": "KAZAMA-KUN",
        "_age": "？",
        "_birthday": "？月？日",
        "_bloodType": "？型",
        "_height": "？",
        "_cv": "？？？？",
        "_masterReleaseLabelId": 1
    },
    {
        "_unitTypeId": 139,
        "_name": "ネネちゃん",
        "_nameAlpha": "NENE-CHAN",
        "_age": "？",
        "_birthday": "？月？日",
        "_bloodType": "？型",
        "_height": "？",
        "_cv": "？？？？",
        "_masterReleaseLabelId": 1
    },
    {
        "_unitTypeId": 140,
        "_name": "マサオくん",
        "_nameAlpha": "MASAO-KUN",
        "_age": "？",
        "_birthday": "？月？日",
        "_bloodType": "？型",
        "_height": "？",
        "_cv": "？？？？",
        "_masterReleaseLabelId": 1
    },
    {
        "_unitTypeId": 143,
        "_name": "玲",
        "_nameAlpha": "LEI",
        "_age": "？",
        "_birthday": "？月？日",
        "_bloodType": "？型",
        "_height": "？",
        "_cv": "？？？？",
        "_masterReleaseLabelId": 1
    },
    {
        "_unitTypeId": 144,
        "_name": "エリザベス",
        "_nameAlpha": "ELIZABETH",
        "_age": "？",
        "_birthday": "？月？日",
        "_bloodType": "？型",
        "_height": "？",
        "_cv": "？？？？",
        "_masterReleaseLabelId": 1
    },
    {
        "_unitTypeId": 145,
        "_name": "マリー",
        "_nameAlpha": "MARIE",
        "_age": "？",
        "_birthday": "？月？日",
        "_bloodType": "？型",
        "_height": "？",
        "_cv": "？？？？",
        "_masterReleaseLabelId": 1
    },
    {
        "_unitTypeId": 146,
        "_name": "マーガレット",
        "_nameAlpha": "MARGARET",
        "_age": "？",
        "_birthday": "？月？日",
        "_bloodType": "？型",
        "_height": "？",
        "_cv": "？？？？",
        "_masterReleaseLabelId": 1
    },
    {
        "_unitTypeId": 147,
        "_name": "ひかり",
        "_nameAlpha": "HIKARI",
        "_age": "？",
        "_birthday": "？月？日",
        "_bloodType": "？型",
        "_height": "？",
        "_cv": "？？？？",
        "_masterReleaseLabelId": 1
    },
    {
        "_unitTypeId": 148,
        "_name": "ナギ",
        "_nameAlpha": "NAGI",
        "_age": "？",
        "_birthday": "？月？日",
        "_bloodType": "？型",
        "_height": "？",
        "_cv": "？？？？",
        "_masterReleaseLabelId": 1
    },
    {
        "_unitTypeId": 149,
        "_name": "エリザベス",
        "_nameAlpha": "ELIZABETH",
        "_age": "？",
        "_birthday": "？月？日",
        "_bloodType": "？型",
        "_height": "？",
        "_cv": "？？？？",
        "_masterReleaseLabelId": 1
    },
    {
        "_unitTypeId": 150,
        "_name": "マーガレット",
        "_nameAlpha": "MARGARET",
        "_age": "？",
        "_birthday": "？月？日",
        "_bloodType": "？型",
        "_height": "？",
        "_cv": "？？？？",
        "_masterReleaseLabelId": 1
    },
    {
        "_unitTypeId": 151,
        "_name": "ジュスティーヌ＆カロリーヌ",
        "_nameAlpha": "JUSTINE & CAROLINE",
        "_age": "？",
        "_birthday": "？月？日",
        "_bloodType": "？型",
        "_height": "？",
        "_cv": "？？？？",
        "_masterReleaseLabelId": 1
    },
    {
        "_unitTypeId": 152,
        "_name": "岳羽ゆかり",
        "_nameAlpha": "YUKARI TAKEBA",
        "_age": "？",
        "_birthday": "？月？日",
        "_bloodType": "？型",
        "_height": "？",
        "_cv": "？？？？",
        "_masterReleaseLabelId": 1
    },
    {
        "_unitTypeId": 153,
        "_name": "桐条美鶴",
        "_nameAlpha": "MITSURU KIRIJO",
        "_age": "？",
        "_birthday": "？月？日",
        "_bloodType": "？型",
        "_height": "？",
        "_cv": "？？？？",
        "_masterReleaseLabelId": 1
    },
    {
        "_unitTypeId": 154,
        "_name": "山岸風花",
        "_nameAlpha": "FUUKA YAMAGISHI",
        "_age": "？",
        "_birthday": "？月？日",
        "_bloodType": "？型",
        "_height": "？",
        "_cv": "？？？？",
        "_masterReleaseLabelId": 1
    },
    {
        "_unitTypeId": 155,
        "_name": "アイギス",
        "_nameAlpha": "AEGIS",
        "_age": "？",
        "_birthday": "？月？日",
        "_bloodType": "？型",
        "_height": "？",
        "_cv": "？？？？",
        "_masterReleaseLabelId": 1
    },
    {
        "_unitTypeId": 156,
        "_name": "汐見琴音",
        "_nameAlpha": "KOTONE SHIOMI",
        "_age": "？",
        "_birthday": "？月？日",
        "_bloodType": "？型",
        "_height": "？",
        "_cv": "？？？？",
        "_masterReleaseLabelId": 1
    },
    {
        "_unitTypeId": 157,
        "_name": "里中千枝",
        "_nameAlpha": "CHIE SATONAKA",
        "_age": "？",
        "_birthday": "？月？日",
        "_bloodType": "？型",
        "_height": "？",
        "_cv": "？？？？",
        "_masterReleaseLabelId": 1
    },
    {
        "_unitTypeId": 158,
        "_name": "天城雪子",
        "_nameAlpha": "YUKIKO AMAGI",
        "_age": "？",
        "_birthday": "？月？日",
        "_bloodType": "？型",
        "_height": "？",
        "_cv": "？？？？",
        "_masterReleaseLabelId": 1
    },
    {
        "_unitTypeId": 159,
        "_name": "久慈川りせ",
        "_nameAlpha": "RISE KUJIKAWA",
        "_age": "？",
        "_birthday": "？月？日",
        "_bloodType": "？型",
        "_height": "？",
        "_cv": "？？？？",
        "_masterReleaseLabelId": 1
    },
    {
        "_unitTypeId": 160,
        "_name": "白鐘直斗",
        "_nameAlpha": "NAOTO SHIROGANE",
        "_age": "？",
        "_birthday": "？月？日",
        "_bloodType": "？型",
        "_height": "？",
        "_cv": "？？？？",
        "_masterReleaseLabelId": 1
    },
    {
        "_unitTypeId": 161,
        "_name": "マリー",
        "_nameAlpha": "MARIE",
        "_age": "？",
        "_birthday": "？月？日",
        "_bloodType": "？型",
        "_height": "？",
        "_cv": "？？？？",
        "_masterReleaseLabelId": 1
    },
    {
        "_unitTypeId": 162,
        "_name": "パンサー",
        "_nameAlpha": "PANTHER",
        "_age": "？",
        "_birthday": "？月？日",
        "_bloodType": "？型",
        "_height": "？",
        "_cv": "？？？？",
        "_masterReleaseLabelId": 1
    },
    {
        "_unitTypeId": 163,
        "_name": "クイーン",
        "_nameAlpha": "QUEEN",
        "_age": "？",
        "_birthday": "？月？日",
        "_bloodType": "？型",
        "_height": "？",
        "_cv": "？？？？",
        "_masterReleaseLabelId": 1
    },
    {
        "_unitTypeId": 164,
        "_name": "ナビ",
        "_nameAlpha": "ORACLE",
        "_age": "？",
        "_birthday": "？月？日",
        "_bloodType": "？型",
        "_height": "？",
        "_cv": "？？？？",
        "_masterReleaseLabelId": 1
    },
    {
        "_unitTypeId": 165,
        "_name": "ノワール",
        "_nameAlpha": "NOIR",
        "_age": "？",
        "_birthday": "？月？日",
        "_bloodType": "？型",
        "_height": "？",
        "_cv": "？？？？",
        "_masterReleaseLabelId": 1
    },
    {
        "_unitTypeId": 166,
        "_name": "ヴァイオレット",
        "_nameAlpha": "VIOLET",
        "_age": "？",
        "_birthday": "？月？日",
        "_bloodType": "？型",
        "_height": "？",
        "_cv": "？？？？",
        "_masterReleaseLabelId": 1
    },
    {
        "_unitTypeId": 167,
        "_name": "エリザベス",
        "_nameAlpha": "ELIZABETH",
        "_age": "？",
        "_birthday": "？月？日",
        "_bloodType": "？型",
        "_height": "？",
        "_cv": "？？？？",
        "_masterReleaseLabelId": 1
    },
    {
        "_unitTypeId": 168,
        "_name": "カレン",
        "_nameAlpha": "Kallen",
        "_age": "？",
        "_birthday": "？月？日",
        "_bloodType": "？型",
        "_height": "？",
        "_cv": "？？？？",
        "_masterReleaseLabelId": 1
    },
    {
        "_unitTypeId": 169,
        "_name": "シャーリー",
        "_nameAlpha": "Shirley",
        "_age": "？",
        "_birthday": "？月？日",
        "_bloodType": "？型",
        "_height": "？",
        "_cv": "？？？？",
        "_masterReleaseLabelId": 1
    },
    {
        "_unitTypeId": 170,
        "_name": "C.C.",
        "_nameAlpha": "C.C.",
        "_age": "？",
        "_birthday": "？月？日",
        "_bloodType": "？型",
        "_height": "？",
        "_cv": "？？？？",
        "_masterReleaseLabelId": 1
    },
    {
        "_unitTypeId": 171,
        "_name": "コーネリア",
        "_nameAlpha": "Cornelia",
        "_age": "？",
        "_birthday": "？月？日",
        "_bloodType": "？型",
        "_height": "？",
        "_cv": "？？？？",
        "_masterReleaseLabelId": 1
    },
    {
        "_unitTypeId": 172,
        "_name": "ユーフェミア",
        "_nameAlpha": "Euphemia",
        "_age": "？",
        "_birthday": "？月？日",
        "_bloodType": "？型",
        "_height": "？",
        "_cv": "？？？？",
        "_masterReleaseLabelId": 1
    },
    {
        "_unitTypeId": 173,
        "_name": "ナナリー",
        "_nameAlpha": "Nunnally",
        "_age": "？",
        "_birthday": "？月？日",
        "_bloodType": "？型",
        "_height": "？",
        "_cv": "？？？？",
        "_masterReleaseLabelId": 1
    },
    {
        "_unitTypeId": 174,
        "_name": "ヴィレッタ",
        "_nameAlpha": "Villetta",
        "_age": "？",
        "_birthday": "？月？日",
        "_bloodType": "？型",
        "_height": "？",
        "_cv": "？？？？",
        "_masterReleaseLabelId": 1
    },
    {
        "_unitTypeId": 175,
        "_name": "咲世子",
        "_nameAlpha": "Sayoko",
        "_age": "？",
        "_birthday": "？月？日",
        "_bloodType": "？型",
        "_height": "？",
        "_cv": "？？？？",
        "_masterReleaseLabelId": 1
    },
    {
        "_unitTypeId": 176,
        "_name": "アーニャ",
        "_nameAlpha": "Anya",
        "_age": "？",
        "_birthday": "？月？日",
        "_bloodType": "？型",
        "_height": "？",
        "_cv": "？？？？",
        "_masterReleaseLabelId": 1
    },
    {
        "_unitTypeId": 191,
        "_name": "高海千歌",
        "_nameAlpha": "CHIKA TAKAMI",
        "_age": "？",
        "_birthday": "8月1日",
        "_bloodType": "Ｂ型",
        "_height": "？",
        "_cv": "伊波杏樹",
        "_masterReleaseLabelId": 1
    },
    {
        "_unitTypeId": 192,
        "_name": "桜内梨子",
        "_nameAlpha": "RIKO SAKURAUCHI",
        "_age": "？",
        "_birthday": "9月19日",
        "_bloodType": "Ａ型",
        "_height": "？",
        "_cv": "逢田梨香子",
        "_masterReleaseLabelId": 1
    },
    {
        "_unitTypeId": 193,
        "_name": "松浦果南",
        "_nameAlpha": "KANAN MATSUURA",
        "_age": "？",
        "_birthday": "2月10日",
        "_bloodType": "Ｏ型",
        "_height": "？",
        "_cv": "諏訪ななか",
        "_masterReleaseLabelId": 1
    },
    {
        "_unitTypeId": 194,
        "_name": "黒澤ダイヤ",
        "_nameAlpha": "DIA KUROSAWA",
        "_age": "？",
        "_birthday": "1月1日",
        "_bloodType": "Ａ型",
        "_height": "？",
        "_cv": "小宮有紗",
        "_masterReleaseLabelId": 1
    },
    {
        "_unitTypeId": 195,
        "_name": "渡辺曜",
        "_nameAlpha": "YOU WATANABE",
        "_age": "？",
        "_birthday": "4月17日",
        "_bloodType": "ＡＢ型",
        "_height": "？",
        "_cv": "斉藤朱夏",
        "_masterReleaseLabelId": 1
    },
    {
        "_unitTypeId": 196,
        "_name": "津島善子",
        "_nameAlpha": "YOSHIKO TSUSHIMA",
        "_age": "？",
        "_birthday": "7月13日",
        "_bloodType": "Ｏ型",
        "_height": "？",
        "_cv": "小林愛香",
        "_masterReleaseLabelId": 1
    },
    {
        "_unitTypeId": 197,
        "_name": "国木田花丸",
        "_nameAlpha": "HANAMARU KUNIKIDA",
        "_age": "？",
        "_birthday": "3月4日",
        "_bloodType": "Ｏ型",
        "_height": "？",
        "_cv": "高槻かなこ",
        "_masterReleaseLabelId": 1
    },
    {
        "_unitTypeId": 198,
        "_name": "小原鞠莉",
        "_nameAlpha": "MARI OHARA",
        "_age": "？",
        "_birthday": "6月13日",
        "_bloodType": "ＡＢ型",
        "_height": "？",
        "_cv": "鈴木愛奈",
        "_masterReleaseLabelId": 1
    },
    {
        "_unitTypeId": 199,
        "_name": "黒澤ルビィ",
        "_nameAlpha": "RUBY KUROSAWA",
        "_age": "？",
        "_birthday": "9月21日",
        "_bloodType": "Ａ型",
        "_height": "？",
        "_cv": "降幡 愛",
        "_masterReleaseLabelId": 1
    },
    {
        "_unitTypeId": 201,
        "_name": "上原歩夢",
        "_nameAlpha": "AYUMU UEHARA",
        "_age": "2",
        "_birthday": "3月1日",
        "_bloodType": "Ａ型",
        "_height": "159",
        "_cv": "大西亜玖璃",
        "_masterReleaseLabelId": 1
    },
    {
        "_unitTypeId": 202,
        "_name": "中須かすみ",
        "_nameAlpha": "KASUMI NAKASU",
        "_age": "1",
        "_birthday": "1月23日",
        "_bloodType": "Ｂ型",
        "_height": "155",
        "_cv": "相良茉優",
        "_masterReleaseLabelId": 1
    },
    {
        "_unitTypeId": 203,
        "_name": "桜坂しずく",
        "_nameAlpha": "SHIZUKU OSAKA",
        "_age": "1",
        "_birthday": "4月3日",
        "_bloodType": "Ａ型",
        "_height": "157",
        "_cv": "前田佳織里",
        "_masterReleaseLabelId": 1
    },
    {
        "_unitTypeId": 204,
        "_name": "朝香果林",
        "_nameAlpha": "KARIN ASAKA",
        "_age": "3",
        "_birthday": "6月29日",
        "_bloodType": "ＡＢ型",
        "_height": "167",
        "_cv": "久保田未夢",
        "_masterReleaseLabelId": 1
    },
    {
        "_unitTypeId": 205,
        "_name": "宮下愛",
        "_nameAlpha": "AI MIYASHITA",
        "_age": "2",
        "_birthday": "5月30日",
        "_bloodType": "Ａ型",
        "_height": "163",
        "_cv": "村上奈津実",
        "_masterReleaseLabelId": 1
    },
    {
        "_unitTypeId": 206,
        "_name": "近江彼方",
        "_nameAlpha": "KANATA KONOE",
        "_age": "3",
        "_birthday": "12月16日",
        "_bloodType": "Ｏ型",
        "_height": "158",
        "_cv": "鬼頭明里",
        "_masterReleaseLabelId": 1
    },
    {
        "_unitTypeId": 207,
        "_name": "優木せつ菜",
        "_nameAlpha": "SETSUNA YUKI",
        "_age": "2",
        "_birthday": "8月8日",
        "_bloodType": "Ｏ型",
        "_height": "154",
        "_cv": "林 鼓子",
        "_masterReleaseLabelId": 1
    },
    {
        "_unitTypeId": 208,
        "_name": "エマ・ヴェルデ",
        "_nameAlpha": "EMMA VERDE",
        "_age": "3",
        "_birthday": "2月5日",
        "_bloodType": "Ｏ型",
        "_height": "166",
        "_cv": "指出毬亜",
        "_masterReleaseLabelId": 1
    },
    {
        "_unitTypeId": 209,
        "_name": "天王寺璃奈",
        "_nameAlpha": "RINA TENNOJI",
        "_age": "1",
        "_birthday": "11月13日",
        "_bloodType": "Ｂ型",
        "_height": "149",
        "_cv": "田中ちえ美",
        "_masterReleaseLabelId": 1
    },
    {
        "_unitTypeId": 210,
        "_name": "川本美里",
        "_nameAlpha": "MISATO KAWAMOTO",
        "_age": "？",
        "_birthday": "？月？日",
        "_bloodType": "？型",
        "_height": "？",
        "_cv": "？？？？",
        "_masterReleaseLabelId": 1
    },
    {
        "_unitTypeId": 211,
        "_name": "夏川マイ",
        "_nameAlpha": "MAI NATSUKAWA",
        "_age": "？",
        "_birthday": "？月？日",
        "_bloodType": "？型",
        "_height": "？",
        "_cv": "？？？？",
        "_masterReleaseLabelId": 1
    },
    {
        "_unitTypeId": 212,
        "_name": "三船栞子",
        "_nameAlpha": "SHIORIKO MIFUNE",
        "_age": "1",
        "_birthday": "10月5日",
        "_bloodType": "ＡＢ型",
        "_height": "160",
        "_cv": "小泉萌香",
        "_masterReleaseLabelId": 1
    },
    {
        "_unitTypeId": 213,
        "_name": "ショウ・ランジュ",
        "_nameAlpha": "LANZHU ZHONG",
        "_age": "2",
        "_birthday": "2月15日",
        "_bloodType": "Ｂ型",
        "_height": "165",
        "_cv": "法元明菜",
        "_masterReleaseLabelId": 1
    },
    {
        "_unitTypeId": 214,
        "_name": "ミア・テイラー",
        "_nameAlpha": "MIA TAYLOR",
        "_age": "3",
        "_birthday": "12月6日",
        "_bloodType": "ＡＢ型",
        "_height": "156",
        "_cv": "内田 秀",
        "_masterReleaseLabelId": 1
    },
    {
        "_unitTypeId": 301,
        "_name": "澁谷かのん",
        "_nameAlpha": "KANON SHIBUYA",
        "_age": "1",
        "_birthday": "5月1日",
        "_bloodType": "Ａ型",
        "_height": "159",
        "_cv": "伊達さゆり",
        "_masterReleaseLabelId": 1
    },
    {
        "_unitTypeId": 302,
        "_name": "唐可可",
        "_nameAlpha": "KEKE TANG",
        "_age": "1",
        "_birthday": "7月17日",
        "_bloodType": "Ｏ型",
        "_height": "159",
        "_cv": "Liyuu",
        "_masterReleaseLabelId": 1
    },
    {
        "_unitTypeId": 303,
        "_name": "嵐千砂都",
        "_nameAlpha": "CHISATO ARASHI",
        "_age": "1",
        "_birthday": "2月25日",
        "_bloodType": "Ｂ型",
        "_height": "155",
        "_cv": "岬 なこ",
        "_masterReleaseLabelId": 1
    },
    {
        "_unitTypeId": 304,
        "_name": "平安名すみれ",
        "_nameAlpha": "SUMIRE HEANNA",
        "_age": "1",
        "_birthday": "9月28日",
        "_bloodType": "ＡＢ型",
        "_height": "161",
        "_cv": "ペイトン尚未",
        "_masterReleaseLabelId": 1
    },
    {
        "_unitTypeId": 305,
        "_name": "葉月恋",
        "_nameAlpha": "REN HAZUKI",
        "_age": "1",
        "_birthday": "11月24日",
        "_bloodType": "Ａ型",
        "_height": "163",
        "_cv": "青山なぎさ",
        "_masterReleaseLabelId": 1
    },
    {
        "_unitTypeId": 306,
        "_name": "桜小路きな子",
        "_nameAlpha": "Kinako Sakurakoji",
        "_age": "1",
        "_birthday": "4月10日",
        "_bloodType": "Ｏ型",
        "_height": "159",
        "_cv": "鈴原希実",
        "_masterReleaseLabelId": 1
    },
    {
        "_unitTypeId": 307,
        "_name": "米女メイ",
        "_nameAlpha": "Mei Yoneme",
        "_age": "1",
        "_birthday": "10月29日",
        "_bloodType": "Ａ型",
        "_height": "155",
        "_cv": "薮島朱音",
        "_masterReleaseLabelId": 1
    },
    {
        "_unitTypeId": 308,
        "_name": "若菜四季",
        "_nameAlpha": "Shiki Wakana",
        "_age": "1",
        "_birthday": "6月17日",
        "_bloodType": "Ｂ型",
        "_height": "161",
        "_cv": "大熊和奏",
        "_masterReleaseLabelId": 1
    },
    {
        "_unitTypeId": 309,
        "_name": "鬼塚夏美",
        "_nameAlpha": "Natsumi Onitsuka",
        "_age": "1",
        "_birthday": "8月7日",
        "_bloodType": "ＡＢ型",
        "_height": "152",
        "_cv": "絵森 彩",
        "_masterReleaseLabelId": 1
    },
    {
        "_unitTypeId": 311,
        "_name": "聖澤悠奈",
        "_nameAlpha": "Yuuna Hijirisawa",
        "_age": "？",
        "_birthday": "？月？日",
        "_bloodType": "？型",
        "_height": "？",
        "_cv": "吉武千颯",
        "_masterReleaseLabelId": 1
    },
    {
        "_unitTypeId": 312,
        "_name": "柊摩央",
        "_nameAlpha": "Mao Hiiragi",
        "_age": "？",
        "_birthday": "？月？日",
        "_bloodType": "？型",
        "_height": "？",
        "_cv": "結木ゆな",
        "_masterReleaseLabelId": 1
    },
    {
        "_unitTypeId": 313,
        "_name": "さや",
        "_nameAlpha": "Saya",
        "_age": "？",
        "_birthday": "？月？日",
        "_bloodType": "？型",
        "_height": "？",
        "_cv": "？？？？",
        "_masterReleaseLabelId": 1
    },
    {
        "_unitTypeId": 314,
        "_name": "ナナミ",
        "_nameAlpha": "Nanami",
        "_age": "？",
        "_birthday": "？月？日",
        "_bloodType": "？型",
        "_height": "？",
        "_cv": "？？？？",
        "_masterReleaseLabelId": 1
    },
    {
        "_unitTypeId": 315,
        "_name": "ヤエ",
        "_nameAlpha": "Yae",
        "_age": "？",
        "_birthday": "？月？日",
        "_bloodType": "？型",
        "_height": "？",
        "_cv": "？？？？",
        "_masterReleaseLabelId": 1
    },
    {
        "_unitTypeId": 316,
        "_name": "ココノ",
        "_nameAlpha": "Kokono",
        "_age": "？",
        "_birthday": "？月？日",
        "_bloodType": "？型",
        "_height": "？",
        "_cv": "？？？？",
        "_masterReleaseLabelId": 1
    },
    {
        "_unitTypeId": 317,
        "_name": "理事長",
        "_nameAlpha": "Director",
        "_age": "？",
        "_birthday": "？月？日",
        "_bloodType": "？型",
        "_height": "？",
        "_cv": "？？？？",
        "_masterReleaseLabelId": 1
    },
    {
        "_unitTypeId": 318,
        "_name": "澁谷ありあ",
        "_nameAlpha": "Aria Shibuya",
        "_age": "？",
        "_birthday": "？月？日",
        "_bloodType": "？型",
        "_height": "？",
        "_cv": "？？？？",
        "_masterReleaseLabelId": 1
    },
    {
        "_unitTypeId": 319,
        "_name": "かのんの母",
        "_nameAlpha": "Kanon's mother",
        "_age": "？",
        "_birthday": "？月？日",
        "_bloodType": "？型",
        "_height": "？",
        "_cv": "？？？？",
        "_masterReleaseLabelId": 1
    },
    {
        "_unitTypeId": 320,
        "_name": "マンマル",
        "_nameAlpha": "Manmaru",
        "_age": "？",
        "_birthday": "？月？日",
        "_bloodType": "？型",
        "_height": "？",
        "_cv": "？？？？",
        "_masterReleaseLabelId": 1
    },
    {
        "_unitTypeId": 321,
        "_name": "チビ",
        "_nameAlpha": "Chibi",
        "_age": "？",
        "_birthday": "？月？日",
        "_bloodType": "？型",
        "_height": "？",
        "_cv": "？？？？",
        "_masterReleaseLabelId": 1
    },
    {
        "_unitTypeId": 501,
        "_name": "C.C.",
        "_nameAlpha": "C.C.",
        "_age": "？",
        "_birthday": "？月？日",
        "_bloodType": "？型",
        "_height": "？",
        "_cv": "？？？？",
        "_masterReleaseLabelId": 1
    },
    {
        "_unitTypeId": 502,
        "_name": "アーニャ",
        "_nameAlpha": "Anya",
        "_age": "？",
        "_birthday": "？月？日",
        "_bloodType": "？型",
        "_height": "？",
        "_cv": "？？？？",
        "_masterReleaseLabelId": 1
    },
    {
        "_unitTypeId": 503,
        "_name": "ヴィレッタ",
        "_nameAlpha": "Villetta",
        "_age": "？",
        "_birthday": "？月？日",
        "_bloodType": "？型",
        "_height": "？",
        "_cv": "？？？？",
        "_masterReleaseLabelId": 1
    },
    {
        "_unitTypeId": 504,
        "_name": "カレン",
        "_nameAlpha": "Kallen",
        "_age": "？",
        "_birthday": "？月？日",
        "_bloodType": "？型",
        "_height": "？",
        "_cv": "？？？？",
        "_masterReleaseLabelId": 1
    },
    {
        "_unitTypeId": 505,
        "_name": "コーネリア",
        "_nameAlpha": "Cornelia",
        "_age": "？",
        "_birthday": "？月？日",
        "_bloodType": "？型",
        "_height": "？",
        "_cv": "？？？？",
        "_masterReleaseLabelId": 1
    },
    {
        "_unitTypeId": 506,
        "_name": "シャーリー",
        "_nameAlpha": "Shirley",
        "_age": "？",
        "_birthday": "？月？日",
        "_bloodType": "？型",
        "_height": "？",
        "_cv": "？？？？",
        "_masterReleaseLabelId": 1
    },
    {
        "_unitTypeId": 507,
        "_name": "セシル",
        "_nameAlpha": "Cecile",
        "_age": "？",
        "_birthday": "？月？日",
        "_bloodType": "？型",
        "_height": "？",
        "_cv": "？？？？",
        "_masterReleaseLabelId": 1
    },
    {
        "_unitTypeId": 508,
        "_name": "ナナリー",
        "_nameAlpha": "Nunnally",
        "_age": "？",
        "_birthday": "？月？日",
        "_bloodType": "？型",
        "_height": "？",
        "_cv": "？？？？",
        "_masterReleaseLabelId": 1
    },
    {
        "_unitTypeId": 509,
        "_name": "ニーナ",
        "_nameAlpha": "Nina",
        "_age": "？",
        "_birthday": "？月？日",
        "_bloodType": "？型",
        "_height": "？",
        "_cv": "？？？？",
        "_masterReleaseLabelId": 1
    },
    {
        "_unitTypeId": 510,
        "_name": "ノネット",
        "_nameAlpha": "Nonette",
        "_age": "？",
        "_birthday": "？月？日",
        "_bloodType": "？型",
        "_height": "？",
        "_cv": "？？？？",
        "_masterReleaseLabelId": 1
    },
    {
        "_unitTypeId": 511,
        "_name": "マリアンヌ",
        "_nameAlpha": "Marianne",
        "_age": "？",
        "_birthday": "？月？日",
        "_bloodType": "？型",
        "_height": "？",
        "_cv": "？？？？",
        "_masterReleaseLabelId": 1
    },
    {
        "_unitTypeId": 512,
        "_name": "ミレイ",
        "_nameAlpha": "Milly",
        "_age": "？",
        "_birthday": "？月？日",
        "_bloodType": "？型",
        "_height": "？",
        "_cv": "？？？？",
        "_masterReleaseLabelId": 1
    },
    {
        "_unitTypeId": 513,
        "_name": "モニカ",
        "_nameAlpha": "Monica",
        "_age": "？",
        "_birthday": "？月？日",
        "_bloodType": "？型",
        "_height": "？",
        "_cv": "？？？？",
        "_masterReleaseLabelId": 1
    },
    {
        "_unitTypeId": 514,
        "_name": "ユーフェミア",
        "_nameAlpha": "Euphemia",
        "_age": "？",
        "_birthday": "？月？日",
        "_bloodType": "？型",
        "_height": "？",
        "_cv": "？？？？",
        "_masterReleaseLabelId": 1
    },
    {
        "_unitTypeId": 515,
        "_name": "ラクシャータ",
        "_nameAlpha": "Rakshata",
        "_age": "？",
        "_birthday": "？月？日",
        "_bloodType": "？型",
        "_height": "？",
        "_cv": "？？？？",
        "_masterReleaseLabelId": 1
    },
    {
        "_unitTypeId": 516,
        "_name": "ローマイヤ",
        "_nameAlpha": "Lohmeyer",
        "_age": "？",
        "_birthday": "？月？日",
        "_bloodType": "？型",
        "_height": "？",
        "_cv": "？？？？",
        "_masterReleaseLabelId": 1
    },
    {
        "_unitTypeId": 517,
        "_name": "咲世子",
        "_nameAlpha": "Sayoko",
        "_age": "？",
        "_birthday": "？月？日",
        "_bloodType": "？型",
        "_height": "？",
        "_cv": "？？？？",
        "_masterReleaseLabelId": 1
    },
    {
        "_unitTypeId": 518,
        "_name": "周香凛",
        "_nameAlpha": "Zhou Xianglin",
        "_age": "？",
        "_birthday": "？月？日",
        "_bloodType": "？型",
        "_height": "？",
        "_cv": "？？？？",
        "_masterReleaseLabelId": 1
    },
    {
        "_unitTypeId": 519,
        "_name": "神楽那",
        "_nameAlpha": "Kaguya",
        "_age": "？",
        "_birthday": "？月？日",
        "_bloodType": "？型",
        "_height": "？",
        "_cv": "？？？？",
        "_masterReleaseLabelId": 1
    },
    {
        "_unitTypeId": 520,
        "_name": "千葉凪沙",
        "_nameAlpha": "Nagisa Chiba",
        "_age": "？",
        "_birthday": "？月？日",
        "_bloodType": "？型",
        "_height": "？",
        "_cv": "？？？？",
        "_masterReleaseLabelId": 1
    },
    {
        "_unitTypeId": 521,
        "_name": "天子",
        "_nameAlpha": "Emperor",
        "_age": "？",
        "_birthday": "？月？日",
        "_bloodType": "？型",
        "_height": "？",
        "_cv": "？？？？",
        "_masterReleaseLabelId": 1
    },
    {
        "_unitTypeId": 522,
        "_name": "シャムナ",
        "_nameAlpha": "Shamuna",
        "_age": "？",
        "_birthday": "？月？日",
        "_bloodType": "？型",
        "_height": "？",
        "_cv": "？？？？",
        "_masterReleaseLabelId": 1
    },
    {
        "_unitTypeId": 901,
        "_name": "高坂穂乃果",
        "_nameAlpha": "HONOKA KOSAKA",
        "_age": "？",
        "_birthday": "8月3日",
        "_bloodType": "Ｏ型",
        "_height": "？",
        "_cv": "新田恵海",
        "_masterReleaseLabelId": 1
    },
    {
        "_unitTypeId": 902,
        "_name": "絢瀬絵里",
        "_nameAlpha": "ELI AYASE",
        "_age": "？",
        "_birthday": "10月21日",
        "_bloodType": "Ｂ型",
        "_height": "？",
        "_cv": "南條愛乃",
        "_masterReleaseLabelId": 1
    },
    {
        "_unitTypeId": 903,
        "_name": "南ことり",
        "_nameAlpha": "KOTORI MINAMI",
        "_age": "？",
        "_birthday": "9月12日",
        "_bloodType": "Ｏ型",
        "_height": "？",
        "_cv": "内田 彩",
        "_masterReleaseLabelId": 1
    },
    {
        "_unitTypeId": 904,
        "_name": "園田海未",
        "_nameAlpha": "UMI SONODA",
        "_age": "？",
        "_birthday": "3月15日",
        "_bloodType": "Ａ型",
        "_height": "？",
        "_cv": "三森すずこ",
        "_masterReleaseLabelId": 1
    },
    {
        "_unitTypeId": 905,
        "_name": "星空凛",
        "_nameAlpha": "RIN HOSHIZORA",
        "_age": "？",
        "_birthday": "11月1日",
        "_bloodType": "Ａ型",
        "_height": "？",
        "_cv": "飯田里穂",
        "_masterReleaseLabelId": 1
    },
    {
        "_unitTypeId": 906,
        "_name": "西木野真姫",
        "_nameAlpha": "MAKI NISHIKINO",
        "_age": "？",
        "_birthday": "4月19日",
        "_bloodType": "ＡＢ型",
        "_height": "？",
        "_cv": "Pile",
        "_masterReleaseLabelId": 1
    },
    {
        "_unitTypeId": 907,
        "_name": "東條希",
        "_nameAlpha": "NOZOMI TOJO",
        "_age": "？",
        "_birthday": "6月9日",
        "_bloodType": "Ｏ型",
        "_height": "？",
        "_cv": "楠田亜衣奈",
        "_masterReleaseLabelId": 1
    },
    {
        "_unitTypeId": 908,
        "_name": "小泉花陽",
        "_nameAlpha": "HANAYO KOIZUMI",
        "_age": "？",
        "_birthday": "1月17日",
        "_bloodType": "Ｂ型",
        "_height": "？",
        "_cv": "久保ユリカ",
        "_masterReleaseLabelId": 1
    },
    {
        "_unitTypeId": 909,
        "_name": "矢澤にこ",
        "_nameAlpha": "NICO YAZAWA",
        "_age": "？",
        "_birthday": "7月22日",
        "_bloodType": "Ａ型",
        "_height": "？",
        "_cv": "徳井青空",
        "_masterReleaseLabelId": 1
    },
    {
        "_unitTypeId": 911,
        "_name": "高海千歌",
        "_nameAlpha": "CHIKA TAKAMI",
        "_age": "？",
        "_birthday": "8月1日",
        "_bloodType": "Ｂ型",
        "_height": "？",
        "_cv": "伊波杏樹",
        "_masterReleaseLabelId": 1
    },
    {
        "_unitTypeId": 912,
        "_name": "桜内梨子",
        "_nameAlpha": "RIKO SAKURAUCHI",
        "_age": "？",
        "_birthday": "9月19日",
        "_bloodType": "Ａ型",
        "_height": "？",
        "_cv": "逢田梨香子",
        "_masterReleaseLabelId": 1
    },
    {
        "_unitTypeId": 913,
        "_name": "松浦果南",
        "_nameAlpha": "KANAN MATSUURA",
        "_age": "？",
        "_birthday": "2月10日",
        "_bloodType": "Ｏ型",
        "_height": "？",
        "_cv": "諏訪ななか",
        "_masterReleaseLabelId": 1
    },
    {
        "_unitTypeId": 914,
        "_name": "黒澤ダイヤ",
        "_nameAlpha": "DIA KUROSAWA",
        "_age": "？",
        "_birthday": "1月1日",
        "_bloodType": "Ａ型",
        "_height": "？",
        "_cv": "小宮有紗",
        "_masterReleaseLabelId": 1
    },
    {
        "_unitTypeId": 915,
        "_name": "渡辺曜",
        "_nameAlpha": "YOU WATANABE",
        "_age": "？",
        "_birthday": "4月17日",
        "_bloodType": "ＡＢ型",
        "_height": "？",
        "_cv": "斉藤朱夏",
        "_masterReleaseLabelId": 1
    },
    {
        "_unitTypeId": 916,
        "_name": "津島善子",
        "_nameAlpha": "YOSHIKO TSUSHIMA",
        "_age": "？",
        "_birthday": "7月13日",
        "_bloodType": "Ｏ型",
        "_height": "？",
        "_cv": "小林愛香",
        "_masterReleaseLabelId": 1
    },
    {
        "_unitTypeId": 917,
        "_name": "国木田花丸",
        "_nameAlpha": "HANAMARU KUNIKIDA",
        "_age": "？",
        "_birthday": "3月4日",
        "_bloodType": "Ｏ型",
        "_height": "？",
        "_cv": "高槻かなこ",
        "_masterReleaseLabelId": 1
    },
    {
        "_unitTypeId": 918,
        "_name": "小原鞠莉",
        "_nameAlpha": "MARI OHARA",
        "_age": "？",
        "_birthday": "6月13日",
        "_bloodType": "ＡＢ型",
        "_height": "？",
        "_cv": "鈴木愛奈",
        "_masterReleaseLabelId": 1
    },
    {
        "_unitTypeId": 919,
        "_name": "黒澤ルビィ",
        "_nameAlpha": "RUBY KUROSAWA",
        "_age": "？",
        "_birthday": "9月21日",
        "_bloodType": "Ａ型",
        "_height": "？",
        "_cv": "降幡 愛",
        "_masterReleaseLabelId": 1
    },
    {
        "_unitTypeId": 921,
        "_name": "高坂穂乃果",
        "_nameAlpha": "HONOKA KOSAKA",
        "_age": "？",
        "_birthday": "8月3日",
        "_bloodType": "Ｏ型",
        "_height": "？",
        "_cv": "新田恵海",
        "_masterReleaseLabelId": 1
    },
    {
        "_unitTypeId": 922,
        "_name": "絢瀬絵里",
        "_nameAlpha": "ELI AYASE",
        "_age": "？",
        "_birthday": "10月21日",
        "_bloodType": "Ｂ型",
        "_height": "？",
        "_cv": "南條愛乃",
        "_masterReleaseLabelId": 1
    },
    {
        "_unitTypeId": 923,
        "_name": "南ことり",
        "_nameAlpha": "KOTORI MINAMI",
        "_age": "？",
        "_birthday": "9月12日",
        "_bloodType": "Ｏ型",
        "_height": "？",
        "_cv": "内田 彩",
        "_masterReleaseLabelId": 1
    },
    {
        "_unitTypeId": 924,
        "_name": "園田海未",
        "_nameAlpha": "UMI SONODA",
        "_age": "？",
        "_birthday": "3月15日",
        "_bloodType": "Ａ型",
        "_height": "？",
        "_cv": "三森すずこ",
        "_masterReleaseLabelId": 1
    },
    {
        "_unitTypeId": 925,
        "_name": "星空凛",
        "_nameAlpha": "RIN HOSHIZORA",
        "_age": "？",
        "_birthday": "11月1日",
        "_bloodType": "Ａ型",
        "_height": "？",
        "_cv": "飯田里穂",
        "_masterReleaseLabelId": 1
    },
    {
        "_unitTypeId": 926,
        "_name": "西木野真姫",
        "_nameAlpha": "MAKI NISHIKINO",
        "_age": "？",
        "_birthday": "4月19日",
        "_bloodType": "ＡＢ型",
        "_height": "？",
        "_cv": "Pile",
        "_masterReleaseLabelId": 1
    },
    {
        "_unitTypeId": 927,
        "_name": "東條希",
        "_nameAlpha": "NOZOMI TOJO",
        "_age": "？",
        "_birthday": "6月9日",
        "_bloodType": "Ｏ型",
        "_height": "？",
        "_cv": "楠田亜衣奈",
        "_masterReleaseLabelId": 1
    },
    {
        "_unitTypeId": 928,
        "_name": "小泉花陽",
        "_nameAlpha": "HANAYO KOIZUMI",
        "_age": "？",
        "_birthday": "1月17日",
        "_bloodType": "Ｂ型",
        "_height": "？",
        "_cv": "久保ユリカ",
        "_masterReleaseLabelId": 1
    },
    {
        "_unitTypeId": 929,
        "_name": "矢澤にこ",
        "_nameAlpha": "NICO YAZAWA",
        "_age": "？",
        "_birthday": "7月22日",
        "_bloodType": "Ａ型",
        "_height": "？",
        "_cv": "徳井青空",
        "_masterReleaseLabelId": 1
    },
    {
        "_unitTypeId": 931,
        "_name": "高海千歌",
        "_nameAlpha": "CHIKA TAKAMI",
        "_age": "？",
        "_birthday": "8月1日",
        "_bloodType": "Ｂ型",
        "_height": "？",
        "_cv": "伊波杏樹",
        "_masterReleaseLabelId": 1
    },
    {
        "_unitTypeId": 932,
        "_name": "桜内梨子",
        "_nameAlpha": "RIKO SAKURAUCHI",
        "_age": "？",
        "_birthday": "9月19日",
        "_bloodType": "Ａ型",
        "_height": "？",
        "_cv": "逢田梨香子",
        "_masterReleaseLabelId": 1
    },
    {
        "_unitTypeId": 933,
        "_name": "松浦果南",
        "_nameAlpha": "KANAN MATSUURA",
        "_age": "？",
        "_birthday": "2月10日",
        "_bloodType": "Ｏ型",
        "_height": "？",
        "_cv": "諏訪ななか",
        "_masterReleaseLabelId": 1
    },
    {
        "_unitTypeId": 934,
        "_name": "黒澤ダイヤ",
        "_nameAlpha": "DIA KUROSAWA",
        "_age": "？",
        "_birthday": "1月1日",
        "_bloodType": "Ａ型",
        "_height": "？",
        "_cv": "小宮有紗",
        "_masterReleaseLabelId": 1
    },
    {
        "_unitTypeId": 935,
        "_name": "渡辺曜",
        "_nameAlpha": "YOU WATANABE",
        "_age": "？",
        "_birthday": "4月17日",
        "_bloodType": "ＡＢ型",
        "_height": "？",
        "_cv": "斉藤朱夏",
        "_masterReleaseLabelId": 1
    },
    {
        "_unitTypeId": 936,
        "_name": "津島善子",
        "_nameAlpha": "YOSHIKO TSUSHIMA",
        "_age": "？",
        "_birthday": "7月13日",
        "_bloodType": "Ｏ型",
        "_height": "？",
        "_cv": "小林愛香",
        "_masterReleaseLabelId": 1
    },
    {
        "_unitTypeId": 937,
        "_name": "国木田花丸",
        "_nameAlpha": "HANAMARU KUNIKIDA",
        "_age": "？",
        "_birthday": "3月4日",
        "_bloodType": "Ｏ型",
        "_height": "？",
        "_cv": "高槻かなこ",
        "_masterReleaseLabelId": 1
    },
    {
        "_unitTypeId": 938,
        "_name": "小原鞠莉",
        "_nameAlpha": "MARI OHARA",
        "_age": "？",
        "_birthday": "6月13日",
        "_bloodType": "ＡＢ型",
        "_height": "？",
        "_cv": "鈴木愛奈",
        "_masterReleaseLabelId": 1
    },
    {
        "_unitTypeId": 939,
        "_name": "黒澤ルビィ",
        "_nameAlpha": "RUBY KUROSAWA",
        "_age": "？",
        "_birthday": "9月21日",
        "_bloodType": "Ａ型",
        "_height": "？",
        "_cv": "降幡 愛",
        "_masterReleaseLabelId": 1
    },
    {
        "_unitTypeId": 940,
        "_name": "高海千歌",
        "_nameAlpha": "CHIKA TAKAMI",
        "_age": "？",
        "_birthday": "8月1日",
        "_bloodType": "Ｂ型",
        "_height": "？",
        "_cv": "伊波杏樹",
        "_masterReleaseLabelId": 1
    },
    {
        "_unitTypeId": 941,
        "_name": "桜内梨子",
        "_nameAlpha": "RIKO SAKURAUCHI",
        "_age": "？",
        "_birthday": "9月19日",
        "_bloodType": "Ａ型",
        "_height": "？",
        "_cv": "逢田梨香子",
        "_masterReleaseLabelId": 1
    },
    {
        "_unitTypeId": 942,
        "_name": "松浦果南",
        "_nameAlpha": "KANAN MATSUURA",
        "_age": "？",
        "_birthday": "2月10日",
        "_bloodType": "Ｏ型",
        "_height": "？",
        "_cv": "諏訪ななか",
        "_masterReleaseLabelId": 1
    },
    {
        "_unitTypeId": 943,
        "_name": "黒澤ダイヤ",
        "_nameAlpha": "DIA KUROSAWA",
        "_age": "？",
        "_birthday": "1月1日",
        "_bloodType": "Ａ型",
        "_height": "？",
        "_cv": "小宮有紗",
        "_masterReleaseLabelId": 1
    },
    {
        "_unitTypeId": 944,
        "_name": "渡辺曜",
        "_nameAlpha": "YOU WATANABE",
        "_age": "？",
        "_birthday": "4月17日",
        "_bloodType": "ＡＢ型",
        "_height": "？",
        "_cv": "斉藤朱夏",
        "_masterReleaseLabelId": 1
    },
    {
        "_unitTypeId": 945,
        "_name": "津島善子",
        "_nameAlpha": "YOSHIKO TSUSHIMA",
        "_age": "？",
        "_birthday": "7月13日",
        "_bloodType": "Ｏ型",
        "_height": "？",
        "_cv": "小林愛香",
        "_masterReleaseLabelId": 1
    },
    {
        "_unitTypeId": 946,
        "_name": "国木田花丸",
        "_nameAlpha": "HANAMARU KUNIKIDA",
        "_age": "？",
        "_birthday": "3月4日",
        "_bloodType": "Ｏ型",
        "_height": "？",
        "_cv": "高槻かなこ",
        "_masterReleaseLabelId": 1
    },
    {
        "_unitTypeId": 947,
        "_name": "小原鞠莉",
        "_nameAlpha": "MARI OHARA",
        "_age": "？",
        "_birthday": "6月13日",
        "_bloodType": "ＡＢ型",
        "_height": "？",
        "_cv": "鈴木愛奈",
        "_masterReleaseLabelId": 1
    },
    {
        "_unitTypeId": 948,
        "_name": "黒澤ルビィ",
        "_nameAlpha": "RUBY KUROSAWA",
        "_age": "？",
        "_birthday": "9月21日",
        "_bloodType": "Ａ型",
        "_height": "？",
        "_cv": "降幡 愛",
        "_masterReleaseLabelId": 1
    },
    {
        "_unitTypeId": 949,
        "_name": "高坂穂乃果",
        "_nameAlpha": "Honoka Kosaka",
        "_age": "？",
        "_birthday": "8月3日",
        "_bloodType": "Ｏ型",
        "_height": "？",
        "_cv": "新田恵海",
        "_masterReleaseLabelId": 1
    },
    {
        "_unitTypeId": 950,
        "_name": "絢瀬絵里",
        "_nameAlpha": "Eli Ayase",
        "_age": "？",
        "_birthday": "10月21日",
        "_bloodType": "Ｂ型",
        "_height": "？",
        "_cv": "南條愛乃",
        "_masterReleaseLabelId": 1
    },
    {
        "_unitTypeId": 951,
        "_name": "南ことり",
        "_nameAlpha": "Kotori Minami",
        "_age": "？",
        "_birthday": "9月12日",
        "_bloodType": "Ｏ型",
        "_height": "？",
        "_cv": "内田 彩",
        "_masterReleaseLabelId": 1
    },
    {
        "_unitTypeId": 952,
        "_name": "園田海未",
        "_nameAlpha": "Umi Sonoda",
        "_age": "？",
        "_birthday": "3月15日",
        "_bloodType": "Ａ型",
        "_height": "？",
        "_cv": "三森すずこ",
        "_masterReleaseLabelId": 1
    },
    {
        "_unitTypeId": 953,
        "_name": "星空凛",
        "_nameAlpha": "Rin Hoshizora",
        "_age": "？",
        "_birthday": "11月1日",
        "_bloodType": "Ａ型",
        "_height": "？",
        "_cv": "飯田里穂",
        "_masterReleaseLabelId": 1
    },
    {
        "_unitTypeId": 954,
        "_name": "西木野真姫",
        "_nameAlpha": "Maki Nishikino",
        "_age": "？",
        "_birthday": "4月19日",
        "_bloodType": "ＡＢ型",
        "_height": "？",
        "_cv": "Pile",
        "_masterReleaseLabelId": 1
    },
    {
        "_unitTypeId": 955,
        "_name": "東條希",
        "_nameAlpha": "Nozomi Tojo",
        "_age": "？",
        "_birthday": "6月9日",
        "_bloodType": "Ｏ型",
        "_height": "？",
        "_cv": "楠田亜衣奈",
        "_masterReleaseLabelId": 1
    },
    {
        "_unitTypeId": 956,
        "_name": "小泉花陽",
        "_nameAlpha": "Hanayo Koizumi",
        "_age": "？",
        "_birthday": "1月17日",
        "_bloodType": "Ｂ型",
        "_height": "？",
        "_cv": "久保ユリカ",
        "_masterReleaseLabelId": 1
    },
    {
        "_unitTypeId": 957,
        "_name": "矢澤にこ",
        "_nameAlpha": "Nico Yazawa",
        "_age": "？",
        "_birthday": "7月22日",
        "_bloodType": "Ａ型",
        "_height": "？",
        "_cv": "徳井青空",
        "_masterReleaseLabelId": 1
    }
]